ragdaemon/__init__.py
ragdaemon/__main__.py
ragdaemon/app.py
ragdaemon/cerebrus.py
ragdaemon/context.py
ragdaemon/daemon.py
ragdaemon/errors.py
ragdaemon/get_paths.py
ragdaemon/graph.py
ragdaemon/locate.py
ragdaemon/utils.py
ragdaemon/annotators/__init__.py
ragdaemon/annotators/base_annotator.py
ragdaemon/annotators/call_graph.py
ragdaemon/annotators/diff.py
ragdaemon/annotators/hierarchy.py
ragdaemon/annotators/layout_hierarchy.py
ragdaemon/annotators/summarizer.py
ragdaemon/annotators/chunker/__init__.py
ragdaemon/annotators/chunker/chunk_astroid.py
ragdaemon/annotators/chunker/chunk_line.py
ragdaemon/annotators/chunker/chunk_llm.py
ragdaemon/annotators/chunker/utils.py
ragdaemon/database/__init__.py
ragdaemon/database/chroma_database.py
ragdaemon/database/database.py
ragdaemon/database/lite_database.py
ragdaemon/database/pg_database.py
ragdaemon/io/__init__.py
ragdaemon/io/docker_io.py
ragdaemon/io/file_like.py
ragdaemon/io/local_io.py
ragdaemon/prompts/call_graph.toml
ragdaemon/prompts/cerebrus.txt
ragdaemon/prompts/chunk_llm.toml
ragdaemon/prompts/locate.toml
ragdaemon/prompts/summarizer/base.txt
ragdaemon/prompts/summarizer/chunk.txt
ragdaemon/prompts/summarizer/directory.txt
ragdaemon/prompts/summarizer/file.txt
ragdaemon/prompts/summarizer/root.txt
ragdaemon/prompts/summarizer/user.txt
ragdaemon/static/favicon.ico
ragdaemon/static/js/controlPanel.js
ragdaemon/static/js/main.js
ragdaemon/static/js/three/camera.js
ragdaemon/static/js/three/controls.js
ragdaemon/static/js/three/edge.js
ragdaemon/static/js/three/node.js
ragdaemon/static/js/three/raycaster.js
ragdaemon/static/js/three/renderer.js
ragdaemon/static/js/three/scene.js
ragdaemon/templates/index.html
ragdaemon/templates/search_results.html
ragdaemon-0.8.3.dist-info/METADATA
ragdaemon-0.8.3.dist-info/WHEEL
ragdaemon-0.8.3.dist-info/entry_points.txt
ragdaemon-0.8.3.dist-info/licenses/LICENSE
ragdaemon-0.8.3.dist-info/RECORD
