Metadata-Version: 2.3
Name: ragdaemon
Version: 0.8.3
Summary: Generate and render a call graph for a Python project.
Project-URL: Homepage, https://github.com/AbanteAI/ragdaemon
License-File: LICENSE
Classifier: License :: OSI Approved :: MIT License
Classifier: Operating System :: OS Independent
Classifier: Programming Language :: Python :: 3
Requires-Python: >=3.10
Requires-Dist: astroid==3.2.2
Requires-Dist: chromadb==0.4.24
Requires-Dist: dict2xml==1.7.5
Requires-Dist: docker==7.1.0
Requires-Dist: fastapi==0.109.2
Requires-Dist: jinja2==3.1.3
Requires-Dist: networkx==3.2.1
Requires-Dist: psycopg2-binary==2.9.9
Requires-Dist: rank-bm25==0.2.2
Requires-Dist: spiceai~=0.3.0
Requires-Dist: sqlalchemy==2.0.30
Requires-Dist: starlette==0.36.3
Requires-Dist: tqdm==4.66.2
Requires-Dist: uvicorn==0.29.0
Provides-Extra: dev
Requires-Dist: pyright==1.1.372; extra == 'dev'
Requires-Dist: pytest; extra == 'dev'
Requires-Dist: pytest-asyncio; extra == 'dev'
Requires-Dist: ruff; extra == 'dev'
